wildkcat/__init__.py
wildkcat/cli.py
wildkcat/api/__init__.py
wildkcat/api/api_utilities.py
wildkcat/api/brenda_api.py
wildkcat/api/sabio_rk_api.py
wildkcat/api/uniprot_api.py
wildkcat/machine_learning/__init__.py
wildkcat/machine_learning/catapro.py
wildkcat/processing/__init__.py
wildkcat/processing/extract_kcat.py
wildkcat/processing/predict_kcat.py
wildkcat/processing/retrieve_kcat.py
wildkcat/processing/summary.py
wildkcat/utils/__init__.py
wildkcat/utils/generate_reports.py
wildkcat/utils/manage_warnings.py
wildkcat/utils/matching.py
wildkcat/utils/organism.py
wildkcat/utils/temperature.py
wildkcat-0.1.6.dist-info/METADATA
wildkcat-0.1.6.dist-info/WHEEL
wildkcat-0.1.6.dist-info/entry_points.txt
wildkcat-0.1.6.dist-info/licenses/LICENSE
wildkcat-0.1.6.dist-info/RECORD
