Metadata-Version: 2.4
Name: wildkcat
Version: 0.1.6
Summary: Extract, Retrieve and Predict kcat values for a metabolic model to run enzyme constrained metabolic pipelines.
Project-URL: Homepage, https://github.com/h-escoffier/WILDkCAT
Project-URL: Issues, https://github.com/h-escoffier/WILDkCAT
Author-email: Hugues Escoffier <hugues.escoffier@gmail.com>
License-File: LICENSE
Classifier: License :: OSI Approved :: MIT License
Classifier: Natural Language :: English
Classifier: Operating System :: OS Independent
Classifier: Programming Language :: Python :: 3
Requires-Python: <3.14,>=3.11.1
Requires-Dist: biopython>=1.85
Requires-Dist: cobra>=0.29
Requires-Dist: dotenv>=0.9.9
Requires-Dist: matplotlib>=3.9
Requires-Dist: matplotlib>=3.9.2
Requires-Dist: numpy>=2.0
Requires-Dist: pandas>=2.0
Requires-Dist: plotly>=6.3.0
Requires-Dist: requests>=2.32
Requires-Dist: scipy>=1.14
Requires-Dist: seaborn>=0.13.2
Requires-Dist: tomli>=2.2.1
Requires-Dist: tqdm>=4.67.1
Requires-Dist: typer>=0.16.1
Requires-Dist: zeep>=4.3.1
